bilucci/__init__.py
bilucci/__main__.py
bilucci/bilucci_bot.py
bilucci/version.py
bilucci-0.1.0.dist-info/LICENSE
bilucci-0.1.0.dist-info/METADATA
bilucci-0.1.0.dist-info/WHEEL
bilucci-0.1.0.dist-info/top_level.txt
bilucci-0.1.0.dist-info/RECORD
