Metadata-Version: 2.1
Name: bilucci
Version: 0.1.0
Summary: A simple Telegram bot
Home-page: https://github.com/philomath213/bilucci-bot
Author: Bilal Retiat
Author-email: bilalphilomath@gmail.com
License: UNKNOWN
Platform: UNKNOWN
Classifier: Programming Language :: Python :: 3
Classifier: License :: OSI Approved :: MIT License
Classifier: Operating System :: OS Independent
Requires-Python: >=3.6
Requires-Dist: python-telegram-bot
Requires-Dist: python-datamuse
Requires-Dist: omdb
